todo_txt_mcp/__init__.py
todo_txt_mcp/server.py
todo_txt_mcp/models/__init__.py
todo_txt_mcp/models/config.py
todo_txt_mcp/models/todo.py
todo_txt_mcp/services/__init__.py
todo_txt_mcp/services/file_service.py
todo_txt_mcp/services/todo_service.py
todo_txt_mcp/tools/__init__.py
todo_txt_mcp/tools/crud_tools.py
todo_txt_mcp/tools/list_tools.py
todo_txt_mcp-1.0.2.dist-info/METADATA
todo_txt_mcp-1.0.2.dist-info/WHEEL
todo_txt_mcp-1.0.2.dist-info/entry_points.txt
todo_txt_mcp-1.0.2.dist-info/licenses/LICENSE
todo_txt_mcp-1.0.2.dist-info/RECORD
