Metadata-Version: 2.4
Name: todo-txt-mcp
Version: 1.0.2
Summary: Model Context Protocol server for todo.txt file management with AI assistants like Claude
Project-URL: Homepage, https://github.com/danielmeint/todo-txt-mcp
Project-URL: Documentation, https://github.com/danielmeint/todo-txt-mcp#readme
Project-URL: Repository, https://github.com/danielmeint/todo-txt-mcp.git
Project-URL: Issues, https://github.com/danielmeint/todo-txt-mcp/issues
Project-URL: Changelog, https://github.com/danielmeint/todo-txt-mcp/blob/main/CHANGELOG.md
Author-email: Daniel Meint <pilots-4-trilogy@icloud.com>
Maintainer-email: Daniel Meint <pilots-4-trilogy@icloud.com>
License: MIT License
License-File: LICENSE
Keywords: ai,claude,cli,mcp,model-context-protocol,productivity,task-management,todo,todo.txt
Classifier: Development Status :: 5 - Production/Stable
Classifier: Environment :: Console
Classifier: Intended Audience :: Developers
Classifier: Intended Audience :: End Users/Desktop
Classifier: License :: OSI Approved :: MIT License
Classifier: Operating System :: OS Independent
Classifier: Programming Language :: Python :: 3
Classifier: Programming Language :: Python :: 3.10
Classifier: Programming Language :: Python :: 3.11
Classifier: Programming Language :: Python :: 3.12
Classifier: Programming Language :: Python :: 3.13
Classifier: Topic :: Office/Business :: Scheduling
Classifier: Topic :: Software Development :: Libraries :: Python Modules
Classifier: Topic :: Utilities
Requires-Python: >=3.10
Requires-Dist: mcp[cli]>=1.9.2
Requires-Dist: pydantic-settings>=2.9.0
Requires-Dist: pydantic>=2.11.5
Requires-Dist: pytodotxt>=3.0.0
